scraipe/__init__.py
scraipe/async_classes.py
scraipe/async_util/__init__.py
scraipe/async_util/async_executors.py
scraipe/async_util/async_manager.py
scraipe/async_util/common.py
scraipe/async_util/future_processor.py
scraipe/classes.py
scraipe/common.py
scraipe/defaults/__init__.py
scraipe/defaults/list_link_collector.py
scraipe/defaults/multi_analyzer.py
scraipe/defaults/multi_scraper.py
scraipe/defaults/raw_scraper.py
scraipe/defaults/text_scraper.py
scraipe/defaults/text_stats_analyzer.py
scraipe/extended/__init__.py
scraipe/extended/llm_analyzers/__init__.py
scraipe/extended/llm_analyzers/gemini_analyzer.py
scraipe/extended/llm_analyzers/llm_analyzer_base.py
scraipe/extended/llm_analyzers/openai_analyzer.py
scraipe/extended/news_scraper.py
scraipe/extended/reddit_link_collector.py
scraipe/extended/reddit_submission_scraper.py
scraipe/extended/telegram_message_scraper.py
scraipe/extended/telegram_news_scraper.py
scraipe/workflow.py
scraipe-0.1.73.dist-info/LICENSE
scraipe-0.1.73.dist-info/METADATA
scraipe-0.1.73.dist-info/WHEEL
scraipe-0.1.73.dist-info/RECORD
