Metadata-Version: 2.3
Name: scraipe
Version: 0.1.73
Summary: AI web scraping workflow.
License: MIT
Author: Nibs
Requires-Python: >=3.10,<4.0
Classifier: License :: OSI Approved :: MIT License
Classifier: Programming Language :: Python :: 3
Classifier: Programming Language :: Python :: 3.10
Classifier: Programming Language :: Python :: 3.11
Classifier: Programming Language :: Python :: 3.12
Classifier: Programming Language :: Python :: 3.13
Provides-Extra: extended
Requires-Dist: aiohttp (>=3.11.16,<4.0.0)
Requires-Dist: asyncpraw (>=7.8.0,<8.0.0) ; extra == "extended"
Requires-Dist: bs4 (>=0.0.2,<0.0.3)
Requires-Dist: filelock (>=3.18.0,<4.0.0) ; extra == "extended"
Requires-Dist: google-genai (>=1.9.0,<2.0.0) ; extra == "extended"
Requires-Dist: openai (>=1.68.2,<2.0.0) ; extra == "extended"
Requires-Dist: pandas (>=2.2.3,<3.0.0)
Requires-Dist: pydantic (>=2.10.6,<3.0.0)
Requires-Dist: qrcode (>=8.1,<9.0) ; extra == "extended"
Requires-Dist: telethon (>=1.39.0,<2.0.0) ; extra == "extended"
Requires-Dist: tqdm
Requires-Dist: trafilatura (>=2.0.0,<3.0.0) ; extra == "extended"
Project-URL: Homepage, https://github.com/snpm/scraipe
